{"東京": [{"label": "東京1R", "average": [{"num": "5", "name": "エクスプレスナイト", "avg": 55, "dist": "", "crs": "", "val": 55}], "distance": [{"num": "12", "name": "タイセイゴッシュ", "avg": "", "dist": 77, "crs": "", "val": 77}, {"num": "5", "name": "エクスプレスナイト", "avg": "", "dist": 56, "crs": "", "val": 56}, {"num": "8", "name": "テンノルーキー", "avg": "", "dist": 33, "crs": "", "val": 33}], "course": [{"num": "12", "name": "タイセイゴッシュ", "avg": "", "dist": "", "crs": 77, "val": 77}, {"num": "2", "name": "ライカ", "avg": "", "dist": "", "crs": 72, "val": 72}, {"num": "5", "name": "エクスプレスナイト", "avg": "", "dist": "", "crs": 56, "val": 56}, {"num": "15", "name": "スーホ", "avg": "", "dist": "", "crs": 51, "val": 51}, {"num": "8", "name": "テンノルーキー", "avg": "", "dist": "", "crs": 33, "val": 33}], "triple": [{"num": "5", "name": "エクスプレスナイト", "avg": 55, "dist": 56, "crs": 56}]}, {"label": "東京2R", "average": [{"num": "1", "name": "オウケンシルヴァー", "avg": 83, "dist": "", "crs": "", "val": 83}, {"num": "13", "name": "トレインザマインド", "avg": 83, "dist": "", "crs": "", "val": 83}, {"num": "6", "name": "タケルゴールド", "avg": 81, "dist": "", "crs": "", "val": 81}, {"num": "16", "name": "カージオイド", "avg": 80, "dist": "", "crs": "", "val": 80}, {"num": "7", "name": "スマートクオーレ", "avg": 78, "dist": "", "crs": "", "val": 78}], "distance": [{"num": "13", "name": "トレインザマインド", "avg": "", "dist": 92, "crs": "", "val": 92}, {"num": "7", "name": "スマートクオーレ", "avg": "", "dist": 87, "crs": "", "val": 87}, {"num": "6", "name": "タケルゴールド", "avg": "", "dist": 86, "crs": "", "val": 86}, {"num": "16", "name": "カージオイド", "avg": "", "dist": 85, "crs": "", "val": 85}, {"num": "1", "name": "オウケンシルヴァー", "avg": "", "dist": 84, "crs": "", "val": 84}], "course": [{"num": "13", "name": "トレインザマインド", "avg": "", "dist": "", "crs": 92, "val": 92}, {"num": "7", "name": "スマートクオーレ", "avg": "", "dist": "", "crs": 87, "val": 87}, {"num": "6", "name": "タケルゴールド", "avg": "", "dist": "", "crs": 86, "val": 86}, {"num": "16", "name": "カージオイド", "avg": "", "dist": "", "crs": 85, "val": 85}, {"num": "1", "name": "オウケンシルヴァー", "avg": "", "dist": "", "crs": 84, "val": 84}], "triple": [{"num": "6", "name": "タケルゴールド", "avg": 81, "dist": 86, "crs": 86}, {"num": "13", "name": "トレインザマインド", "avg": 83, "dist": 92, "crs": 92}]}, {"label": "東京3R", "average": [{"num": "16", "name": "リアライズタキオン", "avg": 65, "dist": "", "crs": "", "val": 65}], "distance": [{"num": "8", "name": "イナズマダイモン", "avg": "", "dist": 87, "crs": "", "val": 87}, {"num": "16", "name": "リアライズタキオン", "avg": "", "dist": 84, "crs": "", "val": 84}, {"num": "1", "name": "ピードモント", "avg": "", "dist": 77, "crs": "", "val": 77}, {"num": "10", "name": "ドゥーニ", "avg": "", "dist": 70, "crs": "", "val": 70}, {"num": "7", "name": "ポッドスモーカー", "avg": "", "dist": 53, "crs": "", "val": 53}], "course": [{"num": "8", "name": "イナズマダイモン", "avg": "", "dist": "", "crs": 87, "val": 87}, {"num": "16", "name": "リアライズタキオン", "avg": "", "dist": "", "crs": 84, "val": 84}, {"num": "1", "name": "ピードモント", "avg": "", "dist": "", "crs": 77, "val": 77}, {"num": "10", "name": "ドゥーニ", "avg": "", "dist": "", "crs": 70, "val": 70}, {"num": "7", "name": "ポッドスモーカー", "avg": "", "dist": "", "crs": 53, "val": 53}], "triple": [{"num": "16", "name": "リアライズタキオン", "avg": 65, "dist": 84, "crs": 84}]}, {"label": "東京4R", "average": [], "distance": [], "course": [], "triple": []}, {"label": "東京5R", "average": [], "distance": [{"num": "10", "name": "ヨドノティアラ", "avg": "", "dist": 79, "crs": "", "val": 79}, {"num": "14", "name": "レゲンデ", "avg": "", "dist": 70, "crs": "", "val": 70}, {"num": "7", "name": "ダイシンレスター", "avg": "", "dist": 61, "crs": "", "val": 61}, {"num": "8", "name": "ケイツータカ", "avg": "", "dist": 58, "crs": "", "val": 58}], "course": [{"num": "10", "name": "ヨドノティアラ", "avg": "", "dist": "", "crs": 79, "val": 79}, {"num": "6", "name": "サンデースマッシュ", "avg": "", "dist": "", "crs": 77, "val": 77}, {"num": "13", "name": "タイキプレジール", "avg": "", "dist": "", "crs": 72, "val": 72}, {"num": "14", "name": "レゲンデ", "avg": "", "dist": "", "crs": 70, "val": 70}, {"num": "2", "name": "ヤマニンアレシス", "avg": "", "dist": "", "crs": 66, "val": 66}], "triple": []}, {"label": "東京6R", "average": [{"num": "12", "name": "ソルトバーン", "avg": 55, "dist": "", "crs": "", "val": 55}], "distance": [{"num": "5", "name": "マンサニージャ", "avg": "", "dist": 77, "crs": "", "val": 77}, {"num": "12", "name": "ソルトバーン", "avg": "", "dist": 76, "crs": "", "val": 76}, {"num": "1", "name": "スカーレットジーン", "avg": "", "dist": 55, "crs": "", "val": 55}], "course": [{"num": "15", "name": "シニャンガ", "avg": "", "dist": "", "crs": 81, "val": 81}, {"num": "8", "name": "ダーリングハースト", "avg": "", "dist": "", "crs": 79, "val": 79}, {"num": "14", "name": "コンサートピアノ", "avg": "", "dist": "", "crs": 79, "val": 79}, {"num": "5", "name": "マンサニージャ", "avg": "", "dist": "", "crs": 77, "val": 77}, {"num": "10", "name": "クイーンズレイン", "avg": "", "dist": "", "crs": 73, "val": 73}], "triple": []}, {"label": "東京7R", "average": [{"num": "16", "name": "グロリアスマーチ", "avg": 81, "dist": "", "crs": "", "val": 81}, {"num": "9", "name": "フォトンゲイザー", "avg": 74, "dist": "", "crs": "", "val": 74}, {"num": "10", "name": "トラスコンガーデン", "avg": 72, "dist": "", "crs": "", "val": 72}], "distance": [{"num": "16", "name": "グロリアスマーチ", "avg": "", "dist": 93, "crs": "", "val": 93}, {"num": "7", "name": "ベレーバスク", "avg": "", "dist": 89, "crs": "", "val": 89}, {"num": "5", "name": "シャオママル", "avg": "", "dist": 85, "crs": "", "val": 85}, {"num": "3", "name": "タイセイアストロ", "avg": "", "dist": 81, "crs": "", "val": 81}, {"num": "15", "name": "リネンタイリン", "avg": "", "dist": 80, "crs": "", "val": 80}], "course": [{"num": "16", "name": "グロリアスマーチ", "avg": "", "dist": "", "crs": 92, "val": 92}, {"num": "5", "name": "シャオママル", "avg": "", "dist": "", "crs": 85, "val": 85}, {"num": "6", "name": "ルージュブリッツ", "avg": "", "dist": "", "crs": 84, "val": 84}, {"num": "15", "name": "リネンタイリン", "avg": "", "dist": "", "crs": 80, "val": 80}, {"num": "11", "name": "シュペルリング", "avg": "", "dist": "", "crs": 77, "val": 77}], "triple": [{"num": "16", "name": "グロリアスマーチ", "avg": 81, "dist": 93, "crs": 92}]}, {"label": "東京8R", "average": [{"num": "5", "name": "チュウワチーフ", "avg": 90, "dist": "", "crs": "", "val": 90}, {"num": "11", "name": "ヘリオトロープ", "avg": 89, "dist": "", "crs": "", "val": 89}, {"num": "6", "name": "エーリアル", "avg": 86, "dist": "", "crs": "", "val": 86}, {"num": "7", "name": "アルドール", "avg": 86, "dist": "", "crs": "", "val": 86}, {"num": "12", "name": "マイティマイティー", "avg": 86, "dist": "", "crs": "", "val": 86}], "distance": [{"num": "2", "name": "アデランテ", "avg": "", "dist": 102, "crs": "", "val": 102}, {"num": "5", "name": "チュウワチーフ", "avg": "", "dist": 100, "crs": "", "val": 100}, {"num": "1", "name": "ファイヴレター", "avg": "", "dist": 98, "crs": "", "val": 98}, {"num": "7", "name": "アルドール", "avg": "", "dist": 96, "crs": "", "val": 96}, {"num": "8", "name": "キョウエイフロイデ", "avg": "", "dist": 96, "crs": "", "val": 96}], "course": [{"num": "2", "name": "アデランテ", "avg": "", "dist": "", "crs": 102, "val": 102}, {"num": "5", "name": "チュウワチーフ", "avg": "", "dist": "", "crs": 100, "val": 100}, {"num": "1", "name": "ファイヴレター", "avg": "", "dist": "", "crs": 98, "val": 98}, {"num": "7", "name": "アルドール", "avg": "", "dist": "", "crs": 96, "val": 96}, {"num": "8", "name": "キョウエイフロイデ", "avg": "", "dist": "", "crs": 96, "val": 96}], "triple": [{"num": "5", "name": "チュウワチーフ", "avg": 90, "dist": 100, "crs": 100}]}, {"label": "東京9R", "average": [{"num": "7", "name": "レッドバンデ", "avg": 98, "dist": "", "crs": "", "val": 98}, {"num": "3", "name": "イクリール", "avg": 91, "dist": "", "crs": "", "val": 91}, {"num": "4", "name": "サトノスカイターフ", "avg": 90, "dist": "", "crs": "", "val": 90}, {"num": "6", "name": "アロンズロッド", "avg": 90, "dist": "", "crs": "", "val": 90}, {"num": "8", "name": "オウケンボルト", "avg": 87, "dist": "", "crs": "", "val": 87}], "distance": [{"num": "6", "name": "アロンズロッド", "avg": "", "dist": 105, "crs": "", "val": 105}, {"num": "3", "name": "イクリール", "avg": "", "dist": 100, "crs": "", "val": 100}, {"num": "1", "name": "ワイズゴールド", "avg": "", "dist": 99, "crs": "", "val": 99}, {"num": "2", "name": "アヴニールドブリエ", "avg": "", "dist": 97, "crs": "", "val": 97}, {"num": "4", "name": "サトノスカイターフ", "avg": "", "dist": 96, "crs": "", "val": 96}], "course": [{"num": "6", "name": "アロンズロッド", "avg": "", "dist": "", "crs": 105, "val": 105}, {"num": "3", "name": "イクリール", "avg": "", "dist": "", "crs": 100, "val": 100}, {"num": "1", "name": "ワイズゴールド", "avg": "", "dist": "", "crs": 99, "val": 99}, {"num": "2", "name": "アヴニールドブリエ", "avg": "", "dist": "", "crs": 97, "val": 97}, {"num": "4", "name": "サトノスカイターフ", "avg": "", "dist": "", "crs": 97, "val": 97}], "triple": [{"num": "3", "name": "イクリール", "avg": 91, "dist": 100, "crs": 100}]}, {"label": "東京10R", "average": [{"num": "10", "name": "ヴァンドーム", "avg": 104, "dist": "", "crs": "", "val": 104}, {"num": "4", "name": "ターコイズフリンジ", "avg": 101, "dist": "", "crs": "", "val": 101}, {"num": "12", "name": "ストレングス", "avg": 98, "dist": "", "crs": "", "val": 98}, {"num": "2", "name": "グラウンドビート", "avg": 96, "dist": "", "crs": "", "val": 96}, {"num": "3", "name": "ガンウルフ", "avg": 96, "dist": "", "crs": "", "val": 96}], "distance": [{"num": "14", "name": "レイズカイザー", "avg": "", "dist": 105, "crs": "", "val": 105}, {"num": "10", "name": "ヴァンドーム", "avg": "", "dist": 104, "crs": "", "val": 104}, {"num": "12", "name": "ストレングス", "avg": "", "dist": 104, "crs": "", "val": 104}, {"num": "7", "name": "ベンヌ", "avg": "", "dist": 101, "crs": "", "val": 101}, {"num": "13", "name": "トクシーカイザー", "avg": "", "dist": 100, "crs": "", "val": 100}], "course": [{"num": "4", "name": "ターコイズフリンジ", "avg": "", "dist": "", "crs": 108, "val": 108}, {"num": "3", "name": "ガンウルフ", "avg": "", "dist": "", "crs": 106, "val": 106}, {"num": "10", "name": "ヴァンドーム", "avg": "", "dist": "", "crs": 106, "val": 106}, {"num": "2", "name": "グラウンドビート", "avg": "", "dist": "", "crs": 105, "val": 105}, {"num": "12", "name": "ストレングス", "avg": "", "dist": "", "crs": 104, "val": 104}], "triple": [{"num": "10", "name": "ヴァンドーム", "avg": 104, "dist": 104, "crs": 106}]}, {"label": "東京11R", "average": [{"num": "11", "name": "レディーゴール", "avg": 82, "dist": "", "crs": "", "val": 82}], "distance": [{"num": "1", "name": "ドリームコア", "avg": "", "dist": 96, "crs": "", "val": 96}, {"num": "9", "name": "ギャラボーグ", "avg": "", "dist": 96, "crs": "", "val": 96}, {"num": "10", "name": "ミツカネベネラ", "avg": "", "dist": 95, "crs": "", "val": 95}, {"num": "5", "name": "ヒズマスターピース", "avg": "", "dist": 93, "crs": "", "val": 93}, {"num": "3", "name": "マルガ", "avg": "", "dist": 91, "crs": "", "val": 91}], "course": [{"num": "1", "name": "ドリームコア", "avg": "", "dist": "", "crs": 96, "val": 96}, {"num": "10", "name": "ミツカネベネラ", "avg": "", "dist": "", "crs": 95, "val": 95}, {"num": "5", "name": "ヒズマスターピース", "avg": "", "dist": "", "crs": 93, "val": 93}, {"num": "3", "name": "マルガ", "avg": "", "dist": "", "crs": 91, "val": 91}, {"num": "11", "name": "レディーゴール", "avg": "", "dist": "", "crs": 91, "val": 91}], "triple": []}, {"label": "東京12R", "average": [{"num": "12", "name": "モティスフォント", "avg": 90, "dist": "", "crs": "", "val": 90}, {"num": "4", "name": "キューティリップ", "avg": 89, "dist": "", "crs": "", "val": 89}, {"num": "5", "name": "チョングク", "avg": 89, "dist": "", "crs": "", "val": 89}, {"num": "1", "name": "ミエノフェアリー", "avg": 86, "dist": "", "crs": "", "val": 86}, {"num": "11", "name": "マニス", "avg": 86, "dist": "", "crs": "", "val": 86}], "distance": [{"num": "3", "name": "レッドレナート", "avg": "", "dist": 98, "crs": "", "val": 98}, {"num": "7", "name": "アルレッキーノ", "avg": "", "dist": 98, "crs": "", "val": 98}, {"num": "9", "name": "シャンクス", "avg": "", "dist": 97, "crs": "", "val": 97}, {"num": "2", "name": "ソニックライン", "avg": "", "dist": 96, "crs": "", "val": 96}, {"num": "12", "name": "モティスフォント", "avg": "", "dist": 96, "crs": "", "val": 96}], "course": [{"num": "7", "name": "アルレッキーノ", "avg": "", "dist": "", "crs": 99, "val": 99}, {"num": "5", "name": "チョングク", "avg": "", "dist": "", "crs": 96, "val": 96}, {"num": "12", "name": "モティスフォント", "avg": "", "dist": "", "crs": 96, "val": 96}, {"num": "11", "name": "マニス", "avg": "", "dist": "", "crs": 95, "val": 95}, {"num": "3", "name": "レッドレナート", "avg": "", "dist": "", "crs": 94, "val": 94}], "triple": []}], "京都": [{"label": "京都1R", "average": [{"num": "9", "name": "ロココ", "avg": 53, "dist": "", "crs": "", "val": 53}], "distance": [{"num": "4", "name": "ウンナターシャ", "avg": "", "dist": 76, "crs": "", "val": 76}, {"num": "9", "name": "ロココ", "avg": "", "dist": 73, "crs": "", "val": 73}, {"num": "10", "name": "リーチグローリー", "avg": "", "dist": 64, "crs": "", "val": 64}, {"num": "11", "name": "ドリームキャリー", "avg": "", "dist": 63, "crs": "", "val": 63}, {"num": "2", "name": "ベンティガスエルテ", "avg": "", "dist": 55, "crs": "", "val": 55}], "course": [{"num": "4", "name": "ウンナターシャ", "avg": "", "dist": "", "crs": 76, "val": 76}, {"num": "10", "name": "リーチグローリー", "avg": "", "dist": "", "crs": 64, "val": 64}, {"num": "11", "name": "ドリームキャリー", "avg": "", "dist": "", "crs": 63, "val": 63}, {"num": "13", "name": "ベルラフィネ", "avg": "", "dist": "", "crs": 42, "val": 42}, {"num": "5", "name": "ジャージーテーラー", "avg": "", "dist": "", "crs": 41, "val": 41}], "triple": []}, {"label": "京都2R", "average": [{"num": "16", "name": "マクアケ", "avg": 56, "dist": "", "crs": "", "val": 56}, {"num": "3", "name": "マインセーラ", "avg": 46, "dist": "", "crs": "", "val": 46}], "distance": [{"num": "15", "name": "メイショウバルク", "avg": "", "dist": 67, "crs": "", "val": 67}, {"num": "12", "name": "ビスケットアソート", "avg": "", "dist": 65, "crs": "", "val": 65}, {"num": "16", "name": "マクアケ", "avg": "", "dist": 62, "crs": "", "val": 62}, {"num": "7", "name": "ディグニダドレアル", "avg": "", "dist": 57, "crs": "", "val": 57}, {"num": "3", "name": "マインセーラ", "avg": "", "dist": 56, "crs": "", "val": 56}], "course": [{"num": "16", "name": "マクアケ", "avg": "", "dist": "", "crs": 66, "val": 66}, {"num": "12", "name": "ビスケットアソート", "avg": "", "dist": "", "crs": 65, "val": 65}, {"num": "15", "name": "メイショウバルク", "avg": "", "dist": "", "crs": 64, "val": 64}, {"num": "14", "name": "イッタレイッタレ", "avg": "", "dist": "", "crs": 63, "val": 63}, {"num": "8", "name": "ミスヘンリー", "avg": "", "dist": "", "crs": 59, "val": 59}], "triple": [{"num": "16", "name": "マクアケ", "avg": 56, "dist": 62, "crs": 66}]}, {"label": "京都3R", "average": [{"num": "8", "name": "ピエナオルカ", "avg": 61, "dist": "", "crs": "", "val": 61}, {"num": "9", "name": "テイエムパイロダン", "avg": 54, "dist": "", "crs": "", "val": 54}], "distance": [{"num": "3", "name": "ダテオトコ", "avg": "", "dist": 62, "crs": "", "val": 62}, {"num": "8", "name": "ピエナオルカ", "avg": "", "dist": 61, "crs": "", "val": 61}, {"num": "2", "name": "リードアクター", "avg": "", "dist": 55, "crs": "", "val": 55}, {"num": "7", "name": "ロードヴェリタス", "avg": "", "dist": 55, "crs": "", "val": 55}], "course": [{"num": "9", "name": "テイエムパイロダン", "avg": "", "dist": "", "crs": 68, "val": 68}, {"num": "3", "name": "ダテオトコ", "avg": "", "dist": "", "crs": 66, "val": 66}, {"num": "8", "name": "ピエナオルカ", "avg": "", "dist": "", "crs": 64, "val": 64}, {"num": "6", "name": "メイショウアカリ", "avg": "", "dist": "", "crs": 63, "val": 63}, {"num": "5", "name": "グロリアス", "avg": "", "dist": "", "crs": 59, "val": 59}], "triple": [{"num": "8", "name": "ピエナオルカ", "avg": 61, "dist": 61, "crs": 64}]}, {"label": "京都4R", "average": [{"num": "5", "name": "キープシャイニング", "avg": 64, "dist": "", "crs": "", "val": 64}, {"num": "8", "name": "ジュディーイメル", "avg": 60, "dist": "", "crs": "", "val": 60}, {"num": "16", "name": "ナウオアネヴァー", "avg": 58, "dist": "", "crs": "", "val": 58}, {"num": "15", "name": "ナブッコ", "avg": 57, "dist": "", "crs": "", "val": 57}], "distance": [{"num": "8", "name": "ジュディーイメル", "avg": "", "dist": 73, "crs": "", "val": 73}, {"num": "5", "name": "キープシャイニング", "avg": "", "dist": 71, "crs": "", "val": 71}, {"num": "11", "name": "シュネープリンセス", "avg": "", "dist": 62, "crs": "", "val": 62}, {"num": "6", "name": "ワイドシャッフエン", "avg": "", "dist": 58, "crs": "", "val": 58}, {"num": "2", "name": "レヴァンターセ", "avg": "", "dist": 56, "crs": "", "val": 56}], "course": [{"num": "5", "name": "キープシャイニング", "avg": "", "dist": "", "crs": 71, "val": 71}, {"num": "16", "name": "ナウオアネヴァー", "avg": "", "dist": "", "crs": 67, "val": 67}, {"num": "11", "name": "シュネープリンセス", "avg": "", "dist": "", "crs": 62, "val": 62}, {"num": "14", "name": "ダンジョンヒーロー", "avg": "", "dist": "", "crs": 59, "val": 59}, {"num": "6", "name": "ワイドシャッフエン", "avg": "", "dist": "", "crs": 58, "val": 58}], "triple": [{"num": "5", "name": "キープシャイニング", "avg": 64, "dist": 71, "crs": 71}]}, {"label": "京都5R", "average": [], "distance": [], "course": [], "triple": []}, {"label": "京都6R", "average": [{"num": "14", "name": "セルリア", "avg": 59, "dist": "", "crs": "", "val": 59}, {"num": "1", "name": "マイネルリーヒム", "avg": 58, "dist": "", "crs": "", "val": 58}], "distance": [{"num": "13", "name": "フレアオブセンス", "avg": "", "dist": 83, "crs": "", "val": 83}, {"num": "15", "name": "ミルトメテオ", "avg": "", "dist": 80, "crs": "", "val": 80}, {"num": "10", "name": "ルンベーラ", "avg": "", "dist": 78, "crs": "", "val": 78}, {"num": "12", "name": "ダノンテムズ", "avg": "", "dist": 78, "crs": "", "val": 78}, {"num": "16", "name": "シートゥサミット", "avg": "", "dist": 76, "crs": "", "val": 76}], "course": [{"num": "17", "name": "モンシーク", "avg": "", "dist": "", "crs": 77, "val": 77}, {"num": "16", "name": "シートゥサミット", "avg": "", "dist": "", "crs": 76, "val": 76}, {"num": "13", "name": "フレアオブセンス", "avg": "", "dist": "", "crs": 63, "val": 63}, {"num": "7", "name": "ファインマン", "avg": "", "dist": "", "crs": 50, "val": 50}, {"num": "6", "name": "ロッククライム", "avg": "", "dist": "", "crs": 49, "val": 49}], "triple": []}, {"label": "京都7R", "average": [{"num": "14", "name": "モズタチアガレ", "avg": 88, "dist": "", "crs": "", "val": 88}, {"num": "2", "name": "エイシンマールス", "avg": 82, "dist": "", "crs": "", "val": 82}, {"num": "5", "name": "タケルハーロック", "avg": 80, "dist": "", "crs": "", "val": 80}, {"num": "15", "name": "シュテルンビルト", "avg": 79, "dist": "", "crs": "", "val": 79}, {"num": "1", "name": "アメリカンビヨンド", "avg": 78, "dist": "", "crs": "", "val": 78}], "distance": [{"num": "14", "name": "モズタチアガレ", "avg": "", "dist": 96, "crs": "", "val": 96}, {"num": "2", "name": "エイシンマールス", "avg": "", "dist": 90, "crs": "", "val": 90}, {"num": "15", "name": "シュテルンビルト", "avg": "", "dist": 88, "crs": "", "val": 88}, {"num": "4", "name": "ミヤジマナ", "avg": "", "dist": 86, "crs": "", "val": 86}, {"num": "6", "name": "カサブランカキッド", "avg": "", "dist": 85, "crs": "", "val": 85}], "course": [{"num": "14", "name": "モズタチアガレ", "avg": "", "dist": "", "crs": 91, "val": 91}, {"num": "2", "name": "エイシンマールス", "avg": "", "dist": "", "crs": 85, "val": 85}, {"num": "12", "name": "クインズメレンゲ", "avg": "", "dist": "", "crs": 83, "val": 83}, {"num": "5", "name": "タケルハーロック", "avg": "", "dist": "", "crs": 82, "val": 82}, {"num": "4", "name": "ミヤジマナ", "avg": "", "dist": "", "crs": 81, "val": 81}], "triple": [{"num": "2", "name": "エイシンマールス", "avg": 82, "dist": 90, "crs": 85}, {"num": "14", "name": "モズタチアガレ", "avg": 88, "dist": 96, "crs": 91}]}, {"label": "京都8R", "average": [{"num": "12", "name": "ソウルアンドジャズ", "avg": 92, "dist": "", "crs": "", "val": 92}, {"num": "5", "name": "ノボリクレバー", "avg": 89, "dist": "", "crs": "", "val": 89}, {"num": "6", "name": "ハッピーダンチャン", "avg": 85, "dist": "", "crs": "", "val": 85}, {"num": "11", "name": "マンダリンボレロ", "avg": 85, "dist": "", "crs": "", "val": 85}, {"num": "2", "name": "レッドボブ", "avg": 84, "dist": "", "crs": "", "val": 84}], "distance": [{"num": "5", "name": "ノボリクレバー", "avg": "", "dist": 94, "crs": "", "val": 94}, {"num": "12", "name": "ソウルアンドジャズ", "avg": "", "dist": 91, "crs": "", "val": 91}, {"num": "2", "name": "レッドボブ", "avg": "", "dist": 89, "crs": "", "val": 89}, {"num": "4", "name": "グランオース", "avg": "", "dist": 88, "crs": "", "val": 88}, {"num": "3", "name": "シュプリンガー", "avg": "", "dist": 87, "crs": "", "val": 87}], "course": [{"num": "10", "name": "タイガースパーク", "avg": "", "dist": "", "crs": 100, "val": 100}, {"num": "2", "name": "レッドボブ", "avg": "", "dist": "", "crs": 98, "val": 98}, {"num": "5", "name": "ノボリクレバー", "avg": "", "dist": "", "crs": 98, "val": 98}, {"num": "3", "name": "シュプリンガー", "avg": "", "dist": "", "crs": 96, "val": 96}, {"num": "12", "name": "ソウルアンドジャズ", "avg": "", "dist": "", "crs": 92, "val": 92}], "triple": [{"num": "5", "name": "ノボリクレバー", "avg": 89, "dist": 94, "crs": 98}]}, {"label": "京都9R", "average": [{"num": "11", "name": "メイショウハッケイ", "avg": 84, "dist": "", "crs": "", "val": 84}, {"num": "6", "name": "トワニ", "avg": 78, "dist": "", "crs": "", "val": 78}], "distance": [{"num": "8", "name": "サトノセプター", "avg": "", "dist": 92, "crs": "", "val": 92}, {"num": "6", "name": "トワニ", "avg": "", "dist": 86, "crs": "", "val": 86}, {"num": "7", "name": "アイガーリー", "avg": "", "dist": 86, "crs": "", "val": 86}, {"num": "9", "name": "チュウワカーネギー", "avg": "", "dist": 85, "crs": "", "val": 85}, {"num": "11", "name": "メイショウハッケイ", "avg": "", "dist": 84, "crs": "", "val": 84}], "course": [{"num": "4", "name": "カレントゥルーシー", "avg": "", "dist": "", "crs": 92, "val": 92}, {"num": "11", "name": "メイショウハッケイ", "avg": "", "dist": "", "crs": 91, "val": 91}, {"num": "1", "name": "ナムラコスモス", "avg": "", "dist": "", "crs": 89, "val": 89}, {"num": "7", "name": "アイガーリー", "avg": "", "dist": "", "crs": 86, "val": 86}, {"num": "3", "name": "シーミハットク", "avg": "", "dist": "", "crs": 75, "val": 75}], "triple": []}, {"label": "京都10R", "average": [{"num": "12", "name": "オールセインツ", "avg": 95, "dist": "", "crs": "", "val": 95}, {"num": "2", "name": "ミラージュナイト", "avg": 93, "dist": "", "crs": "", "val": 93}, {"num": "9", "name": "ミュージシャン", "avg": 93, "dist": "", "crs": "", "val": 93}, {"num": "10", "name": "ロワンディシー", "avg": 93, "dist": "", "crs": "", "val": 93}, {"num": "14", "name": "ジーティーアダマン", "avg": 93, "dist": "", "crs": "", "val": 93}], "distance": [{"num": "10", "name": "ロワンディシー", "avg": "", "dist": 108, "crs": "", "val": 108}, {"num": "14", "name": "ジーティーアダマン", "avg": "", "dist": 106, "crs": "", "val": 106}, {"num": "7", "name": "アレナリア", "avg": "", "dist": 103, "crs": "", "val": 103}, {"num": "12", "name": "オールセインツ", "avg": "", "dist": 102, "crs": "", "val": 102}, {"num": "6", "name": "マイネルエニグマ", "avg": "", "dist": 101, "crs": "", "val": 101}], "course": [{"num": "2", "name": "ミラージュナイト", "avg": "", "dist": "", "crs": 111, "val": 111}, {"num": "10", "name": "ロワンディシー", "avg": "", "dist": "", "crs": 108, "val": 108}, {"num": "12", "name": "オールセインツ", "avg": "", "dist": "", "crs": 106, "val": 106}, {"num": "16", "name": "マイネルラウレア", "avg": "", "dist": "", "crs": 105, "val": 105}, {"num": "11", "name": "ハギノアルデバラン", "avg": "", "dist": "", "crs": 101, "val": 101}], "triple": []}, {"label": "京都11R", "average": [{"num": "14", "name": "チェルビアット", "avg": 98, "dist": "", "crs": "", "val": 98}, {"num": "8", "name": "ジャスティンスカイ", "avg": 97, "dist": "", "crs": "", "val": 97}, {"num": "5", "name": "ソルトクィーン", "avg": 96, "dist": "", "crs": "", "val": 96}, {"num": "6", "name": "ブラックシールド", "avg": 96, "dist": "", "crs": "", "val": 96}, {"num": "1", "name": "ニホンピロキーフ", "avg": 95, "dist": "", "crs": "", "val": 95}], "distance": [{"num": "1", "name": "ニホンピロキーフ", "avg": "", "dist": 108, "crs": "", "val": 108}, {"num": "14", "name": "チェルビアット", "avg": "", "dist": 107, "crs": "", "val": 107}, {"num": "8", "name": "ジャスティンスカイ", "avg": "", "dist": 106, "crs": "", "val": 106}, {"num": "9", "name": "ラケマーダ", "avg": "", "dist": 104, "crs": "", "val": 104}, {"num": "12", "name": "キョウエイブリッサ", "avg": "", "dist": 103, "crs": "", "val": 103}], "course": [{"num": "1", "name": "ニホンピロキーフ", "avg": "", "dist": "", "crs": 108, "val": 108}, {"num": "8", "name": "ジャスティンスカイ", "avg": "", "dist": "", "crs": 106, "val": 106}, {"num": "9", "name": "ラケマーダ", "avg": "", "dist": "", "crs": 103, "val": 103}, {"num": "11", "name": "スズハローム", "avg": "", "dist": "", "crs": 103, "val": 103}, {"num": "3", "name": "セッション", "avg": "", "dist": "", "crs": 102, "val": 102}], "triple": [{"num": "8", "name": "ジャスティンスカイ", "avg": 97, "dist": 106, "crs": 106}]}, {"label": "京都12R", "average": [{"num": "5", "name": "サンライズブレイク", "avg": 79, "dist": "", "crs": "", "val": 79}, {"num": "10", "name": "クインズシャウラ", "avg": 79, "dist": "", "crs": "", "val": 79}, {"num": "8", "name": "アスゴッド", "avg": 76, "dist": "", "crs": "", "val": 76}, {"num": "12", "name": "キープライジング", "avg": 75, "dist": "", "crs": "", "val": 75}, {"num": "7", "name": "インディゴアスール", "avg": 71, "dist": "", "crs": "", "val": 71}], "distance": [{"num": "10", "name": "クインズシャウラ", "avg": "", "dist": 88, "crs": "", "val": 88}, {"num": "7", "name": "インディゴアスール", "avg": "", "dist": 85, "crs": "", "val": 85}, {"num": "12", "name": "キープライジング", "avg": "", "dist": 84, "crs": "", "val": 84}, {"num": "3", "name": "リードプリンシパル", "avg": "", "dist": 83, "crs": "", "val": 83}, {"num": "5", "name": "サンライズブレイク", "avg": "", "dist": 82, "crs": "", "val": 82}], "course": [{"num": "8", "name": "アスゴッド", "avg": "", "dist": "", "crs": 83, "val": 83}, {"num": "5", "name": "サンライズブレイク", "avg": "", "dist": "", "crs": 81, "val": 81}, {"num": "3", "name": "リードプリンシパル", "avg": "", "dist": "", "crs": 80, "val": 80}, {"num": "9", "name": "チムニーパイプ", "avg": "", "dist": "", "crs": 77, "val": 77}, {"num": "7", "name": "インディゴアスール", "avg": "", "dist": "", "crs": 75, "val": 75}], "triple": []}], "小倉": [{"label": "小倉1R", "average": [], "distance": [{"num": "14", "name": "ツァレヴナ", "avg": "", "dist": 61, "crs": "", "val": 61}, {"num": "4", "name": "ブリスフルイヤー", "avg": "", "dist": 60, "crs": "", "val": 60}, {"num": "2", "name": "エンジェルグラース", "avg": "", "dist": 58, "crs": "", "val": 58}, {"num": "1", "name": "モーニングダリア", "avg": "", "dist": 51, "crs": "", "val": 51}, {"num": "8", "name": "チカマヨルキーナ", "avg": "", "dist": 50, "crs": "", "val": 50}], "course": [{"num": "2", "name": "エンジェルグラース", "avg": "", "dist": "", "crs": 58, "val": 58}, {"num": "1", "name": "モーニングダリア", "avg": "", "dist": "", "crs": 51, "val": 51}], "triple": []}, {"label": "小倉2R", "average": [{"num": "1", "name": "マーゴットミスト", "avg": 76, "dist": "", "crs": "", "val": 76}], "distance": [{"num": "1", "name": "マーゴットミスト", "avg": "", "dist": 85, "crs": "", "val": 85}, {"num": "18", "name": "ウインドトリック", "avg": "", "dist": 84, "crs": "", "val": 84}, {"num": "13", "name": "リラベガ", "avg": "", "dist": 81, "crs": "", "val": 81}, {"num": "10", "name": "ドリーマーズ", "avg": "", "dist": 76, "crs": "", "val": 76}, {"num": "15", "name": "ノーブルマドンナ", "avg": "", "dist": 76, "crs": "", "val": 76}], "course": [{"num": "18", "name": "ウインドトリック", "avg": "", "dist": "", "crs": 83, "val": 83}, {"num": "13", "name": "リラベガ", "avg": "", "dist": "", "crs": 81, "val": 81}, {"num": "10", "name": "ドリーマーズ", "avg": "", "dist": "", "crs": 76, "val": 76}, {"num": "15", "name": "ノーブルマドンナ", "avg": "", "dist": "", "crs": 76, "val": 76}, {"num": "8", "name": "ララクレアドルーン", "avg": "", "dist": "", "crs": 74, "val": 74}], "triple": []}, {"label": "小倉3R", "average": [{"num": "11", "name": "チュラヴェール", "avg": 61, "dist": "", "crs": "", "val": 61}], "distance": [{"num": "12", "name": "ミヤフロント", "avg": "", "dist": 73, "crs": "", "val": 73}, {"num": "11", "name": "チュラヴェール", "avg": "", "dist": 70, "crs": "", "val": 70}, {"num": "8", "name": "スイーヴル", "avg": "", "dist": 69, "crs": "", "val": 69}, {"num": "1", "name": "ゴーゴーパンチ", "avg": "", "dist": 67, "crs": "", "val": 67}, {"num": "4", "name": "スマートイデアル", "avg": "", "dist": 61, "crs": "", "val": 61}], "course": [{"num": "12", "name": "ミヤフロント", "avg": "", "dist": "", "crs": 73, "val": 73}, {"num": "11", "name": "チュラヴェール", "avg": "", "dist": "", "crs": 70, "val": 70}, {"num": "8", "name": "スイーヴル", "avg": "", "dist": "", "crs": 69, "val": 69}, {"num": "1", "name": "ゴーゴーパンチ", "avg": "", "dist": "", "crs": 67, "val": 67}, {"num": "4", "name": "スマートイデアル", "avg": "", "dist": "", "crs": 61, "val": 61}], "triple": [{"num": "11", "name": "チュラヴェール", "avg": 61, "dist": 70, "crs": 70}]}, {"label": "小倉4R", "average": [{"num": "1", "name": "ダスク", "avg": 1000, "dist": "", "crs": "", "val": 1000}, {"num": "2", "name": "ボエーム", "avg": 1000, "dist": "", "crs": "", "val": 1000}, {"num": "3", "name": "セイフウサツキ", "avg": 1000, "dist": "", "crs": "", "val": 1000}, {"num": "4", "name": "ディベルティスマン", "avg": 1000, "dist": "", "crs": "", "val": 1000}, {"num": "5", "name": "ヴォンヌヴォー", "avg": 1000, "dist": "", "crs": "", "val": 1000}], "distance": [{"num": "3", "name": "セイフウサツキ", "avg": "", "dist": 1000, "crs": "", "val": 1000}, {"num": "7", "name": "フォルガイル", "avg": "", "dist": 1000, "crs": "", "val": 1000}, {"num": "8", "name": "ベイビーベリッシモ", "avg": "", "dist": 1000, "crs": "", "val": 1000}, {"num": "12", "name": "リオンエトワール", "avg": "", "dist": 1000, "crs": "", "val": 1000}], "course": [{"num": "3", "name": "セイフウサツキ", "avg": "", "dist": "", "crs": 1000, "val": 1000}, {"num": "7", "name": "フォルガイル", "avg": "", "dist": "", "crs": 1000, "val": 1000}, {"num": "8", "name": "ベイビーベリッシモ", "avg": "", "dist": "", "crs": 1000, "val": 1000}, {"num": "12", "name": "リオンエトワール", "avg": "", "dist": "", "crs": 1000, "val": 1000}], "triple": [{"num": "3", "name": "セイフウサツキ", "avg": 1000, "dist": 1000, "crs": 1000}]}, {"label": "小倉5R", "average": [{"num": "7", "name": "ノリマル", "avg": 74, "dist": "", "crs": "", "val": 74}, {"num": "14", "name": "ウインマニフィーク", "avg": 73, "dist": "", "crs": "", "val": 73}, {"num": "11", "name": "ナムラヴンダー", "avg": 69, "dist": "", "crs": "", "val": 69}], "distance": [{"num": "6", "name": "ノンブルドール", "avg": "", "dist": 85, "crs": "", "val": 85}, {"num": "15", "name": "シュプリームレルム", "avg": "", "dist": 85, "crs": "", "val": 85}, {"num": "2", "name": "トリニタリオ", "avg": "", "dist": 83, "crs": "", "val": 83}, {"num": "7", "name": "ノリマル", "avg": "", "dist": 83, "crs": "", "val": 83}, {"num": "13", "name": "グリミスティ", "avg": "", "dist": 82, "crs": "", "val": 82}], "course": [{"num": "6", "name": "ノンブルドール", "avg": "", "dist": "", "crs": 85, "val": 85}, {"num": "15", "name": "シュプリームレルム", "avg": "", "dist": "", "crs": 85, "val": 85}, {"num": "2", "name": "トリニタリオ", "avg": "", "dist": "", "crs": 83, "val": 83}, {"num": "7", "name": "ノリマル", "avg": "", "dist": "", "crs": 83, "val": 83}, {"num": "13", "name": "グリミスティ", "avg": "", "dist": "", "crs": 82, "val": 82}], "triple": []}, {"label": "小倉6R", "average": [{"num": "6", "name": "ケイアイクビラ", "avg": 86, "dist": "", "crs": "", "val": 86}, {"num": "14", "name": "ブライトアゲイン", "avg": 86, "dist": "", "crs": "", "val": 86}, {"num": "12", "name": "ノボリリア", "avg": 82, "dist": "", "crs": "", "val": 82}, {"num": "1", "name": "ダイヤモンド", "avg": 81, "dist": "", "crs": "", "val": 81}, {"num": "15", "name": "レオプルミエール", "avg": 81, "dist": "", "crs": "", "val": 81}], "distance": [{"num": "11", "name": "ラブディーヴァ", "avg": "", "dist": 99, "crs": "", "val": 99}, {"num": "14", "name": "ブライトアゲイン", "avg": "", "dist": 97, "crs": "", "val": 97}, {"num": "2", "name": "マキシマムドライブ", "avg": "", "dist": 95, "crs": "", "val": 95}, {"num": "16", "name": "アルマロクザン", "avg": "", "dist": 95, "crs": "", "val": 95}, {"num": "1", "name": "ダイヤモンド", "avg": "", "dist": 94, "crs": "", "val": 94}], "course": [{"num": "14", "name": "ブライトアゲイン", "avg": "", "dist": "", "crs": 97, "val": 97}, {"num": "11", "name": "ラブディーヴァ", "avg": "", "dist": "", "crs": 96, "val": 96}, {"num": "16", "name": "アルマロクザン", "avg": "", "dist": "", "crs": 95, "val": 95}, {"num": "17", "name": "ベルタソ", "avg": "", "dist": "", "crs": 88, "val": 88}, {"num": "6", "name": "ケイアイクビラ", "avg": "", "dist": "", "crs": 87, "val": 87}], "triple": [{"num": "14", "name": "ブライトアゲイン", "avg": 86, "dist": 97, "crs": 97}]}, {"label": "小倉7R", "average": [{"num": "2", "name": "シュニー", "avg": 88, "dist": "", "crs": "", "val": 88}, {"num": "16", "name": "タマモジャスミン", "avg": 82, "dist": "", "crs": "", "val": 82}, {"num": "3", "name": "アンリーベイビー", "avg": 81, "dist": "", "crs": "", "val": 81}, {"num": "14", "name": "ミサビスケッツ", "avg": 77, "dist": "", "crs": "", "val": 77}, {"num": "13", "name": "ライラックデューン", "avg": 74, "dist": "", "crs": "", "val": 74}], "distance": [{"num": "16", "name": "タマモジャスミン", "avg": "", "dist": 87, "crs": "", "val": 87}, {"num": "14", "name": "ミサビスケッツ", "avg": "", "dist": 84, "crs": "", "val": 84}, {"num": "15", "name": "カルドウェル", "avg": "", "dist": 84, "crs": "", "val": 84}, {"num": "1", "name": "ブーケドグレイス", "avg": "", "dist": 83, "crs": "", "val": 83}, {"num": "4", "name": "クインズセレネ", "avg": "", "dist": 83, "crs": "", "val": 83}], "course": [{"num": "15", "name": "カルドウェル", "avg": "", "dist": "", "crs": 84, "val": 84}, {"num": "4", "name": "クインズセレネ", "avg": "", "dist": "", "crs": 83, "val": 83}, {"num": "3", "name": "アンリーベイビー", "avg": "", "dist": "", "crs": 81, "val": 81}, {"num": "16", "name": "タマモジャスミン", "avg": "", "dist": "", "crs": 79, "val": 79}, {"num": "2", "name": "シュニー", "avg": "", "dist": "", "crs": 72, "val": 72}], "triple": []}, {"label": "小倉8R", "average": [{"num": "1", "name": "ジューンベロシティ", "avg": 1000, "dist": "", "crs": "", "val": 1000}, {"num": "2", "name": "ローディアマント", "avg": 1000, "dist": "", "crs": "", "val": 1000}, {"num": "3", "name": "テイエムマジック", "avg": 1000, "dist": "", "crs": "", "val": 1000}, {"num": "4", "name": "ブラックボイス", "avg": 1000, "dist": "", "crs": "", "val": 1000}, {"num": "5", "name": "フェーングロッテン", "avg": 1000, "dist": "", "crs": "", "val": 1000}], "distance": [{"num": "1", "name": "ジューンベロシティ", "avg": "", "dist": 1000, "crs": "", "val": 1000}, {"num": "2", "name": "ローディアマント", "avg": "", "dist": 1000, "crs": "", "val": 1000}, {"num": "3", "name": "テイエムマジック", "avg": "", "dist": 1000, "crs": "", "val": 1000}, {"num": "4", "name": "ブラックボイス", "avg": "", "dist": 1000, "crs": "", "val": 1000}, {"num": "7", "name": "オールザワールド", "avg": "", "dist": 1000, "crs": "", "val": 1000}], "course": [{"num": "1", "name": "ジューンベロシティ", "avg": "", "dist": "", "crs": 1000, "val": 1000}, {"num": "2", "name": "ローディアマント", "avg": "", "dist": "", "crs": 1000, "val": 1000}, {"num": "3", "name": "テイエムマジック", "avg": "", "dist": "", "crs": 1000, "val": 1000}, {"num": "4", "name": "ブラックボイス", "avg": "", "dist": "", "crs": 1000, "val": 1000}, {"num": "6", "name": "レッドファーロ", "avg": "", "dist": "", "crs": 1000, "val": 1000}], "triple": [{"num": "2", "name": "ローディアマント", "avg": 1000, "dist": 1000, "crs": 1000}, {"num": "3", "name": "テイエムマジック", "avg": 1000, "dist": 1000, "crs": 1000}, {"num": "1", "name": "ジューンベロシティ", "avg": 1000, "dist": 1000, "crs": 1000}]}, {"label": "小倉9R", "average": [{"num": "2", "name": "ブラックハヤテ", "avg": 84, "dist": "", "crs": "", "val": 84}, {"num": "5", "name": "アイドクレース", "avg": 70, "dist": "", "crs": "", "val": 70}], "distance": [{"num": "2", "name": "ブラックハヤテ", "avg": "", "dist": 95, "crs": "", "val": 95}, {"num": "7", "name": "ドッグウッド", "avg": "", "dist": 89, "crs": "", "val": 89}, {"num": "10", "name": "アンソニー", "avg": "", "dist": 80, "crs": "", "val": 80}, {"num": "6", "name": "グレーヌドジョワ", "avg": "", "dist": 79, "crs": "", "val": 79}, {"num": "4", "name": "キッコベッロ", "avg": "", "dist": 74, "crs": "", "val": 74}], "course": [{"num": "7", "name": "ドッグウッド", "avg": "", "dist": "", "crs": 89, "val": 89}, {"num": "5", "name": "アイドクレース", "avg": "", "dist": "", "crs": 87, "val": 87}], "triple": []}, {"label": "小倉10R", "average": [{"num": "4", "name": "ザウリ", "avg": 88, "dist": "", "crs": "", "val": 88}, {"num": "13", "name": "ゼンノツキヨミ", "avg": 85, "dist": "", "crs": "", "val": 85}, {"num": "6", "name": "アネモス", "avg": 83, "dist": "", "crs": "", "val": 83}, {"num": "8", "name": "パールフロント", "avg": 82, "dist": "", "crs": "", "val": 82}, {"num": "3", "name": "パルプフィクション", "avg": 78, "dist": "", "crs": "", "val": 78}], "distance": [{"num": "12", "name": "ディーエスショウマ", "avg": "", "dist": 99, "crs": "", "val": 99}, {"num": "3", "name": "パルプフィクション", "avg": "", "dist": 97, "crs": "", "val": 97}, {"num": "4", "name": "ザウリ", "avg": "", "dist": 96, "crs": "", "val": 96}, {"num": "6", "name": "アネモス", "avg": "", "dist": 95, "crs": "", "val": 95}, {"num": "7", "name": "ホークレア", "avg": "", "dist": 95, "crs": "", "val": 95}], "course": [{"num": "12", "name": "ディーエスショウマ", "avg": "", "dist": "", "crs": 99, "val": 99}, {"num": "3", "name": "パルプフィクション", "avg": "", "dist": "", "crs": 97, "val": 97}, {"num": "4", "name": "ザウリ", "avg": "", "dist": "", "crs": 96, "val": 96}, {"num": "6", "name": "アネモス", "avg": "", "dist": "", "crs": 95, "val": 95}, {"num": "13", "name": "ゼンノツキヨミ", "avg": "", "dist": "", "crs": 94, "val": 94}], "triple": [{"num": "4", "name": "ザウリ", "avg": 88, "dist": 96, "crs": 96}]}, {"label": "小倉11R", "average": [{"num": "18", "name": "ジュンヴァンケット", "avg": 96, "dist": "", "crs": "", "val": 96}, {"num": "2", "name": "コウセキ", "avg": 95, "dist": "", "crs": "", "val": 95}, {"num": "4", "name": "ハートホイップ", "avg": 92, "dist": "", "crs": "", "val": 92}, {"num": "6", "name": "ルーフ", "avg": 92, "dist": "", "crs": "", "val": 92}, {"num": "7", "name": "ベイビーキッス", "avg": 92, "dist": "", "crs": "", "val": 92}], "distance": [{"num": "5", "name": "レオテミス", "avg": "", "dist": 109, "crs": "", "val": 109}, {"num": "16", "name": "ジャスパーディビネ", "avg": "", "dist": 107, "crs": "", "val": 107}, {"num": "2", "name": "コウセキ", "avg": "", "dist": 106, "crs": "", "val": 106}, {"num": "6", "name": "ルーフ", "avg": "", "dist": 105, "crs": "", "val": 105}, {"num": "10", "name": "エマヌエーレ", "avg": "", "dist": 105, "crs": "", "val": 105}], "course": [{"num": "2", "name": "コウセキ", "avg": "", "dist": "", "crs": 106, "val": 106}, {"num": "10", "name": "エマヌエーレ", "avg": "", "dist": "", "crs": 105, "val": 105}, {"num": "15", "name": "トーラスシャイン", "avg": "", "dist": "", "crs": 105, "val": 105}, {"num": "8", "name": "ミルテンベルク", "avg": "", "dist": "", "crs": 103, "val": 103}, {"num": "9", "name": "シュヴェルトライテ", "avg": "", "dist": "", "crs": 101, "val": 101}], "triple": [{"num": "2", "name": "コウセキ", "avg": 95, "dist": 106, "crs": 106}]}, {"label": "小倉12R", "average": [{"num": "12", "name": "シンゼンカガ", "avg": 90, "dist": "", "crs": "", "val": 90}, {"num": "7", "name": "グローブアマランス", "avg": 86, "dist": "", "crs": "", "val": 86}, {"num": "1", "name": "アンドローゼス", "avg": 85, "dist": "", "crs": "", "val": 85}, {"num": "4", "name": "ウインボレロ", "avg": 83, "dist": "", "crs": "", "val": 83}, {"num": "13", "name": "ロジウムエポック", "avg": 82, "dist": "", "crs": "", "val": 82}], "distance": [{"num": "1", "name": "アンドローゼス", "avg": "", "dist": 95, "crs": "", "val": 95}, {"num": "8", "name": "ナムラブーニン", "avg": "", "dist": 95, "crs": "", "val": 95}, {"num": "12", "name": "シンゼンカガ", "avg": "", "dist": 94, "crs": "", "val": 94}, {"num": "9", "name": "パシフィックハイ", "avg": "", "dist": 92, "crs": "", "val": 92}, {"num": "4", "name": "ウインボレロ", "avg": "", "dist": 89, "crs": "", "val": 89}], "course": [{"num": "12", "name": "シンゼンカガ", "avg": "", "dist": "", "crs": 94, "val": 94}, {"num": "1", "name": "アンドローゼス", "avg": "", "dist": "", "crs": 90, "val": 90}, {"num": "14", "name": "ジャグアール", "avg": "", "dist": "", "crs": 87, "val": 87}, {"num": "2", "name": "アクイローネ", "avg": "", "dist": "", "crs": 84, "val": 84}, {"num": "10", "name": "プリンセスロロ", "avg": "", "dist": "", "crs": 83, "val": 83}], "triple": [{"num": "12", "name": "シンゼンカガ", "avg": 90, "dist": 94, "crs": 94}, {"num": "1", "name": "アンドローゼス", "avg": 85, "dist": 95, "crs": 90}]}]}